example_isort_formatting_plugin.py
example_isort_formatting_plugin-0.1.1.dist-info/WHEEL
example_isort_formatting_plugin-0.1.1.dist-info/METADATA
example_isort_formatting_plugin-0.1.1.dist-info/entry_points.txt
example_isort_formatting_plugin-0.1.1.dist-info/RECORD
